tests/__init__.py
vnittest/__init__.py
vnittest/controller.py
vnittest/model.py
vnittest/view.py
vnittest/web_app.py
vnittest/notebooks/vnittest.ipynb
vnittest-0.1.0.dist-info/LICENSE
vnittest-0.1.0.dist-info/METADATA
vnittest-0.1.0.dist-info/WHEEL
vnittest-0.1.0.dist-info/entry_points.txt
vnittest-0.1.0.dist-info/top_level.txt
vnittest-0.1.0.dist-info/RECORD
