Metadata-Version: 2.1
Name: vnittest
Version: 0.1.0
Summary: UI interface for gradient flow visualization
Home-page: https://github.com/thienannguyen-cv/vnittest
Author: Thien An L. Nguyen
Author-email: thienannguyen.cv@gmail.com
License: Apache 2.0
License-File: LICENSE
Requires-Dist: numpy==1.19.5
Requires-Dist: plotly==5.12.0
Requires-Dist: ipywidgets==7.6.5
Requires-Dist: matplotlib==3.3.4
Requires-Dist: voila==0.3.0
